agentevals/__init__.py
agentevals/types.py
agentevals/utils.py
agentevals/graph_trajectory/__init__.py
agentevals/graph_trajectory/llm.py
agentevals/graph_trajectory/strict.py
agentevals/graph_trajectory/utils.py
agentevals/trajectory/__init__.py
agentevals/trajectory/llm.py
agentevals/trajectory/match.py
agentevals/trajectory/strict.py
agentevals/trajectory/subset.py
agentevals/trajectory/superset.py
agentevals/trajectory/unordered.py
agentevals/trajectory/utils.py
agentevals-0.0.8.dist-info/licenses/LICENSE
agentevals-0.0.8.dist-info/METADATA
agentevals-0.0.8.dist-info/WHEEL
agentevals-0.0.8.dist-info/top_level.txt
agentevals-0.0.8.dist-info/RECORD
