Metadata-Version: 2.4
Name: agentevals
Version: 0.0.8
Summary: Open-source evaluators for LLM agents
License: MIT
Requires-Python: >=3.9
License-File: LICENSE
Requires-Dist: openevals>=0.0.20
Dynamic: license-file
